src/TurboType.py
src/__init__.py
TurboType-3.7.dist-info/METADATA
TurboType-3.7.dist-info/WHEEL
TurboType-3.7.dist-info/entry_points.txt
TurboType-3.7.dist-info/top_level.txt
TurboType-3.7.dist-info/RECORD
