Metadata-Version: 2.1
Name: TurboType
Version: 3.7
Summary: A Game for Typing challenge
Author: 1337
Classifier: Programming Language :: Python :: 3
Classifier: License :: OSI Approved :: MIT License
Classifier: Operating System :: OS Independent
Requires-Dist: pygame
